algowalk/__init__.py
algowalk/searching/__init__.py
algowalk/searching/search_context.py
algowalk/searching/search_strategy.py
algowalk/searching/algorithms/__init__.py
algowalk/searching/algorithms/binarysearch.py
algowalk/searching/algorithms/linearsearch.py
algowalk/searching/tracker/__init__.py
algowalk/searching/tracker/search_algo_tracker.py
algowalk/searching/visualiser/__init__.py
algowalk/searching/visualiser/searching_plotly_visualiser.py
algowalk/shared/__init__.py
algowalk/shared/pseudocode/__init__.py
algowalk/shared/pseudocode/pseudocode_builder.py
algowalk/sorting/__init__.py
algowalk/sorting/sort_context.py
algowalk/sorting/sort_strategy.py
algowalk/sorting/algorithms/__init__.py
algowalk/sorting/algorithms/bubblesort.py
algowalk/sorting/algorithms/heapsort.py
algowalk/sorting/tracker/__init__.py
algowalk/sorting/tracker/sort_algorithm_tracker.py
algowalk/sorting/visualiser/__init__.py
algowalk/sorting/visualiser/sorting_visualiser.py
algowalk/utils/__init__.py
algowalk/utils/strategy/__init__.py
algowalk/utils/strategy/algorithm_strategy.py
algowalk/utils/tracker/__init__.py
algowalk/utils/tracker/algo_tracker.py
algowalk/utils/visualizer/__init__.py
algowalk/utils/visualizer/step_visualizer.py
kasturing_testing_lib-2.0.6.dist-info/licenses/LICENSE
kasturing_testing_lib-2.0.6.dist-info/METADATA
kasturing_testing_lib-2.0.6.dist-info/WHEEL
kasturing_testing_lib-2.0.6.dist-info/top_level.txt
kasturing_testing_lib-2.0.6.dist-info/RECORD
